asyncinject/__init__.py
asyncinject/vendored_graphlib.py
asyncinject-0.6.1.dist-info/licenses/LICENSE
asyncinject-0.6.1.dist-info/METADATA
asyncinject-0.6.1.dist-info/WHEEL
asyncinject-0.6.1.dist-info/top_level.txt
asyncinject-0.6.1.dist-info/RECORD
