Metadata-Version: 2.4
Name: asyncinject
Version: 0.6.1
Summary: Run async workflows using pytest-fixtures-style dependency injection
Author: Simon Willison
License-Expression: Apache-2.0
Project-URL: Homepage, https://github.com/simonw/asyncinject
Project-URL: Changelog, https://github.com/simonw/asyncinject/releases
Project-URL: Issues, https://github.com/simonw/asyncinject/issues
Project-URL: CI, https://github.com/simonw/asyncinject/actions
Requires-Python: >=3.10
License-File: LICENSE
Provides-Extra: test
Requires-Dist: pytest; extra == "test"
Requires-Dist: pytest-asyncio; extra == "test"
Dynamic: license-file
